{
  "dram_cache_size": 49,
  "flash_cache_size": 4960,
  "results": [
    {
      "hit": 1675880,
      "iteration": 0,
      "metrics": [
        {
          "admission_treshold": 0,
          "algorithm": "qauto",
          "byte_inserted": 887092,
          "byte_miss": 887092,
          "byte_read": 1675880,
          "byte_reinserted": 523547,
          "hit": 1675880,
          "inserted": 887092,
          "layer": 0,
          "miss_ratio": 0.3461184905648599,
          "reinserted": 523547,
          "req": 2562972
        }
      ],
      "miss_ratio": 0.3461184905648599,
      "req": 2562972
    }
  ],
  "trace": "akamai_sjc.ns267.oracleGeneral.bin.zst"
}