{
  "dram_cache_size": 18,
  "flash_cache_size": 1825,
  "results": [
    {
      "hit": 43593,
      "iteration": 0,
      "metrics": [
        {
          "admission_treshold": 0,
          "algorithm": "sxfifo",
          "byte_inserted": 3356407,
          "byte_miss": 3356407,
          "byte_read": 43593,
          "byte_reinserted": 5923,
          "hit": 43593,
          "inserted": 3356407,
          "layer": 0,
          "miss_ratio": 0.9871785294117648,
          "reinserted": 5923,
          "req": 3400000
        }
      ],
      "miss_ratio": 0.9871785294117648,
      "req": 3400000
    }
  ],
  "trace": "io_traces.ns504.oracleGeneral.zst"
}