{
  "dram_cache_size": 13,
  "flash_cache_size": 1358,
  "results": [
    {
      "hit": 639800,
      "iteration": 0,
      "metrics": [
        {
          "admission_treshold": 0,
          "algorithm": "clock",
          "byte_inserted": 597119,
          "byte_miss": 597119,
          "byte_read": 639800,
          "byte_reinserted": 314816,
          "hit": 639800,
          "inserted": 597119,
          "layer": 0,
          "miss_ratio": 0.4827470513428931,
          "reinserted": 314816,
          "req": 1236919
        }
      ],
      "miss_ratio": 0.4827470513428931,
      "req": 1236919
    }
  ],
  "trace": "tencentBlock.ns15284.oracleGeneral.zst"
}