{
  "dram_cache_size": 29,
  "flash_cache_size": 2909,
  "results": [
    {
      "hit": 2359435,
      "iteration": 0,
      "metrics": [
        {
          "admission_treshold": 0,
          "algorithm": "s3fclock",
          "byte_inserted": 3389267,
          "byte_miss": 3389267,
          "byte_read": 2359435,
          "byte_reinserted": 174858,
          "hit": 2359435,
          "inserted": 3389267,
          "layer": 0,
          "miss_ratio": 0.5895708283365532,
          "reinserted": 174858,
          "req": 5748702
        }
      ],
      "miss_ratio": 0.5895708283365532,
      "req": 5748702
    }
  ],
  "trace": "cf_allcolo.ns992.oracleGeneral.zst"
}