{
  "dram_cache_size": 41,
  "flash_cache_size": 4154,
  "results": [
    {
      "hit": 2678898,
      "iteration": 0,
      "metrics": [
        {
          "admission_treshold": 0,
          "algorithm": "s3fclock",
          "byte_inserted": 1203038,
          "byte_miss": 1203038,
          "byte_read": 2678898,
          "byte_reinserted": 402395,
          "hit": 2678898,
          "inserted": 1203038,
          "layer": 0,
          "miss_ratio": 0.30990670634446316,
          "reinserted": 402395,
          "req": 3881936
        }
      ],
      "miss_ratio": 0.30990670634446316,
      "req": 3881936
    }
  ],
  "trace": "tencentBlock.ns4296.oracleGeneral.zst"
}