{
  "dram_cache_size": 63,
  "flash_cache_size": 6373,
  "results": [
    {
      "hit": 3745489,
      "iteration": 0,
      "metrics": [
        {
          "admission_treshold": 0,
          "algorithm": "q3auto",
          "byte_inserted": 1636460,
          "byte_miss": 1636460,
          "byte_read": 3745489,
          "byte_reinserted": 391326,
          "hit": 3745489,
          "inserted": 1636460,
          "layer": 0,
          "miss_ratio": 0.3040645684305072,
          "reinserted": 391326,
          "req": 5381949
        }
      ],
      "miss_ratio": 0.3040645684305072,
      "req": 5381949
    }
  ],
  "trace": "tencentBlock.ns15372.oracleGeneral.zst"
}