{
  "dram_cache_size": 1,
  "flash_cache_size": 141,
  "results": [
    {
      "hit": 2759038,
      "iteration": 0,
      "metrics": [
        {
          "admission_treshold": 0,
          "algorithm": "sxfifo",
          "byte_inserted": 52942,
          "byte_miss": 52942,
          "byte_read": 2759038,
          "byte_reinserted": 6556,
          "hit": 2759038,
          "inserted": 52942,
          "layer": 0,
          "miss_ratio": 0.018827303181388255,
          "reinserted": 6556,
          "req": 2811980
        }
      ],
      "miss_ratio": 0.018827303181388255,
      "req": 2811980
    }
  ],
  "trace": "cf_allcolo.ns4012.oracleGeneral.zst"
}