{
  "dram_cache_size": 13,
  "flash_cache_size": 1399,
  "results": [
    {
      "hit": 2261460,
      "iteration": 0,
      "metrics": [
        {
          "admission_treshold": 0,
          "algorithm": "s3fclock",
          "byte_inserted": 1832805,
          "byte_miss": 1832805,
          "byte_read": 2261460,
          "byte_reinserted": 913488,
          "hit": 2261460,
          "inserted": 1832805,
          "layer": 0,
          "miss_ratio": 0.4476517763261538,
          "reinserted": 913488,
          "req": 4094265
        }
      ],
      "miss_ratio": 0.4476517763261538,
      "req": 4094265
    }
  ],
  "trace": "sc_knownfors_cache.1.oracleGeneral.sample10.zst"
}