{
  "dram_cache_size": 247,
  "flash_cache_size": 24766,
  "results": [
    {
      "hit": 1108543,
      "iteration": 0,
      "metrics": [
        {
          "admission_treshold": 0,
          "algorithm": "gclock",
          "byte_inserted": 4252489,
          "byte_miss": 4252489,
          "byte_read": 1108543,
          "byte_reinserted": 89616,
          "hit": 1108543,
          "inserted": 4252489,
          "layer": 0,
          "miss_ratio": 0.7932220885829445,
          "reinserted": 89616,
          "req": 5361032
        }
      ],
      "miss_ratio": 0.7932220885829445,
      "req": 5361032
    }
  ],
  "trace": "tencentBlock.ns11622.oracleGeneral.zst"
}