{
  "dram_cache_size": 267,
  "flash_cache_size": 26763,
  "results": [
    {
      "hit": 9345478,
      "iteration": 0,
      "metrics": [
        {
          "admission_treshold": 0,
          "algorithm": "t4auto",
          "byte_inserted": 4145743,
          "byte_miss": 4145743,
          "byte_read": 9345478,
          "byte_reinserted": 2491834,
          "hit": 9345478,
          "inserted": 4145743,
          "layer": 0,
          "miss_ratio": 0.30729190486168745,
          "reinserted": 2491834,
          "req": 13491221
        }
      ],
      "miss_ratio": 0.30729190486168745,
      "req": 13491221
    }
  ],
  "trace": "popular_tweets_by_interests_cache.0.oracleGeneral.sample10.zst"
}