{
  "dram_cache_size": 5,
  "flash_cache_size": 541,
  "results": [
    {
      "hit": 1437694,
      "iteration": 0,
      "metrics": [
        {
          "admission_treshold": 0,
          "algorithm": "g2clock",
          "byte_inserted": 216597,
          "byte_miss": 216597,
          "byte_read": 1437694,
          "byte_reinserted": 125158,
          "hit": 1437694,
          "inserted": 216597,
          "layer": 0,
          "miss_ratio": 0.13093041067139943,
          "reinserted": 125158,
          "req": 1654291
        }
      ],
      "miss_ratio": 0.13093041067139943,
      "req": 1654291
    }
  ],
  "trace": "tencentBlock.ns3754.oracleGeneral.zst"
}