{
  "dram_cache_size": 135,
  "flash_cache_size": 13560,
  "results": [
    {
      "hit": 6617936,
      "iteration": 0,
      "metrics": [
        {
          "admission_treshold": 0,
          "algorithm": "gclock",
          "byte_inserted": 6582064,
          "byte_miss": 6582064,
          "byte_read": 6617936,
          "byte_reinserted": 602917,
          "hit": 6617936,
          "inserted": 6582064,
          "layer": 0,
          "miss_ratio": 0.49864121212121215,
          "reinserted": 602917,
          "req": 13200000
        }
      ],
      "miss_ratio": 0.49864121212121215,
      "req": 13200000
    }
  ],
  "trace": "io_traces.ns223.oracleGeneral.zst"
}