{
  "dram_cache_size": 11,
  "flash_cache_size": 1198,
  "results": [
    {
      "hit": 2770285,
      "iteration": 0,
      "metrics": [
        {
          "admission_treshold": 0,
          "algorithm": "d3clock",
          "byte_inserted": 596951,
          "byte_miss": 596951,
          "byte_read": 2770285,
          "byte_reinserted": 423426,
          "hit": 2770285,
          "inserted": 596951,
          "layer": 0,
          "miss_ratio": 0.17728219821836066,
          "reinserted": 423426,
          "req": 3367236
        }
      ],
      "miss_ratio": 0.17728219821836066,
      "req": 3367236
    }
  ],
  "trace": "tencentBlock.ns3925.oracleGeneral.zst"
}