{
  "dram_cache_size": 1510,
  "flash_cache_size": 151083,
  "results": [
    {
      "hit": 104459772,
      "iteration": 0,
      "metrics": [
        {
          "admission_treshold": 0,
          "algorithm": "s3fclock",
          "byte_inserted": 16286747,
          "byte_miss": 16286747,
          "byte_read": 104459772,
          "byte_reinserted": 3886967,
          "hit": 104459772,
          "inserted": 16286747,
          "layer": 0,
          "miss_ratio": 0.1348837807904011,
          "reinserted": 3886967,
          "req": 120746519
        }
      ],
      "miss_ratio": 0.1348837807904011,
      "req": 120746519
    }
  ],
  "trace": "cf_colo28.ns19.oracleGeneral.zst"
}