{
  "dram_cache_size": 22,
  "flash_cache_size": 2209,
  "results": [
    {
      "hit": 967765,
      "iteration": 0,
      "metrics": [
        {
          "admission_treshold": 0,
          "algorithm": "clock",
          "byte_inserted": 765088,
          "byte_miss": 765088,
          "byte_read": 967765,
          "byte_reinserted": 224355,
          "hit": 967765,
          "inserted": 765088,
          "layer": 0,
          "miss_ratio": 0.44151927486059117,
          "reinserted": 224355,
          "req": 1732853
        }
      ],
      "miss_ratio": 0.44151927486059117,
      "req": 1732853
    }
  ],
  "trace": "tencentBlock.ns22331.oracleGeneral.zst"
}