{
  "dram_cache_size": 14,
  "flash_cache_size": 1417,
  "results": [
    {
      "hit": 800431,
      "iteration": 0,
      "metrics": [
        {
          "admission_treshold": 0,
          "algorithm": "dclock",
          "byte_inserted": 472247,
          "byte_miss": 472247,
          "byte_read": 800431,
          "byte_reinserted": 23852,
          "hit": 800431,
          "inserted": 472247,
          "layer": 0,
          "miss_ratio": 0.3710655798245903,
          "reinserted": 23852,
          "req": 1272678
        }
      ],
      "miss_ratio": 0.3710655798245903,
      "req": 1272678
    }
  ],
  "trace": "tencentBlock.ns22890.oracleGeneral.zst"
}