{
  "dram_cache_size": 13,
  "flash_cache_size": 1377,
  "results": [
    {
      "hit": 2760313,
      "iteration": 0,
      "metrics": [
        {
          "admission_treshold": 0,
          "algorithm": "t3auto",
          "byte_inserted": 2039687,
          "byte_miss": 2039687,
          "byte_read": 2760313,
          "byte_reinserted": 421551,
          "hit": 2760313,
          "inserted": 2039687,
          "layer": 0,
          "miss_ratio": 0.4249347916666667,
          "reinserted": 421551,
          "req": 4800000
        }
      ],
      "miss_ratio": 0.4249347916666667,
      "req": 4800000
    }
  ],
  "trace": "io_traces.ns710.oracleGeneral.zst"
}