{
  "dram_cache_size": 8,
  "flash_cache_size": 895,
  "results": [
    {
      "hit": 1087790,
      "iteration": 0,
      "metrics": [
        {
          "admission_treshold": 0,
          "algorithm": "s3fclock",
          "byte_inserted": 460284,
          "byte_miss": 460284,
          "byte_read": 1087790,
          "byte_reinserted": 59673,
          "hit": 1087790,
          "inserted": 460284,
          "layer": 0,
          "miss_ratio": 0.29732687197123653,
          "reinserted": 59673,
          "req": 1548074
        }
      ],
      "miss_ratio": 0.29732687197123653,
      "req": 1548074
    }
  ],
  "trace": "tencentBlock.ns12141.oracleGeneral.zst"
}