{
  "dram_cache_size": 27,
  "flash_cache_size": 2746,
  "results": [
    {
      "hit": 988483,
      "iteration": 0,
      "metrics": [
        {
          "admission_treshold": 0,
          "algorithm": "gclock",
          "byte_inserted": 700226,
          "byte_miss": 700226,
          "byte_read": 988483,
          "byte_reinserted": 44230,
          "hit": 988483,
          "inserted": 700226,
          "layer": 0,
          "miss_ratio": 0.4146516658583569,
          "reinserted": 44230,
          "req": 1688709
        }
      ],
      "miss_ratio": 0.4146516658583569,
      "req": 1688709
    }
  ],
  "trace": "tencentBlock.ns13392.oracleGeneral.zst"
}