{
  "dram_cache_size": 16,
  "flash_cache_size": 1630,
  "results": [
    {
      "hit": 1712213,
      "iteration": 0,
      "metrics": [
        {
          "admission_treshold": 0,
          "algorithm": "q3auto",
          "byte_inserted": 6128160,
          "byte_miss": 6128160,
          "byte_read": 1712213,
          "byte_reinserted": 110981,
          "hit": 1712213,
          "inserted": 6128160,
          "layer": 0,
          "miss_ratio": 0.7816158746529024,
          "reinserted": 110981,
          "req": 7840373
        }
      ],
      "miss_ratio": 0.7816158746529024,
      "req": 7840373
    }
  ],
  "trace": "tencentBlock.ns9466.oracleGeneral.zst"
}