{
  "dram_cache_size": 47,
  "flash_cache_size": 4705,
  "results": [
    {
      "hit": 2661117,
      "iteration": 0,
      "metrics": [
        {
          "admission_treshold": 0,
          "algorithm": "time-auto",
          "byte_inserted": 1693681,
          "byte_miss": 1693681,
          "byte_read": 2661117,
          "byte_reinserted": 778269,
          "hit": 2661117,
          "inserted": 1693681,
          "layer": 0,
          "miss_ratio": 0.3889229764503428,
          "reinserted": 778269,
          "req": 4354798
        }
      ],
      "miss_ratio": 0.3889229764503428,
      "req": 4354798
    }
  ],
  "trace": "tencentBlock.ns5794.oracleGeneral.zst"
}