{
  "dram_cache_size": 20,
  "flash_cache_size": 2023,
  "results": [
    {
      "hit": 898251,
      "iteration": 0,
      "metrics": [
        {
          "admission_treshold": 0,
          "algorithm": "clock",
          "byte_inserted": 892927,
          "byte_miss": 892927,
          "byte_read": 898251,
          "byte_reinserted": 447646,
          "hit": 898251,
          "inserted": 892927,
          "layer": 0,
          "miss_ratio": 0.4985138272131525,
          "reinserted": 447646,
          "req": 1791178
        }
      ],
      "miss_ratio": 0.4985138272131525,
      "req": 1791178
    }
  ],
  "trace": "tencentBlock.ns19594.oracleGeneral.zst"
}