{
  "dram_cache_size": 21,
  "flash_cache_size": 2180,
  "results": [
    {
      "hit": 2513474,
      "iteration": 0,
      "metrics": [
        {
          "admission_treshold": 0,
          "algorithm": "g2clock",
          "byte_inserted": 722473,
          "byte_miss": 722473,
          "byte_read": 2513474,
          "byte_reinserted": 535968,
          "hit": 2513474,
          "inserted": 722473,
          "layer": 0,
          "miss_ratio": 0.2232647815307235,
          "reinserted": 535968,
          "req": 3235947
        }
      ],
      "miss_ratio": 0.2232647815307235,
      "req": 3235947
    }
  ],
  "trace": "tencentBlock.ns18617.oracleGeneral.zst"
}