{
  "dram_cache_size": 1,
  "flash_cache_size": 197,
  "results": [
    {
      "hit": 1250491,
      "iteration": 0,
      "metrics": [
        {
          "admission_treshold": 0,
          "algorithm": "s3fclock-sequential",
          "byte_inserted": 356969,
          "byte_miss": 356969,
          "byte_read": 1250491,
          "byte_reinserted": 80814,
          "hit": 1250491,
          "inserted": 356969,
          "layer": 0,
          "miss_ratio": 0.22207022258718723,
          "reinserted": 80814,
          "req": 1607460
        }
      ],
      "miss_ratio": 0.22207022258718723,
      "req": 1607460
    }
  ],
  "trace": "akamai_sjc.ns922.oracleGeneral.bin.zst"
}