{
  "dram_cache_size": 18,
  "flash_cache_size": 1894,
  "results": [
    {
      "hit": 1440721,
      "iteration": 0,
      "metrics": [
        {
          "admission_treshold": 0,
          "algorithm": "s3fclock",
          "byte_inserted": 774130,
          "byte_miss": 774130,
          "byte_read": 1440721,
          "byte_reinserted": 25249,
          "hit": 1440721,
          "inserted": 774130,
          "layer": 0,
          "miss_ratio": 0.34951786824486164,
          "reinserted": 25249,
          "req": 2214851
        }
      ],
      "miss_ratio": 0.34951786824486164,
      "req": 2214851
    }
  ],
  "trace": "tencentBlock.ns16450.oracleGeneral.zst"
}