{
  "dram_cache_size": 50,
  "flash_cache_size": 5052,
  "results": [
    {
      "hit": 3469916,
      "iteration": 0,
      "metrics": [
        {
          "admission_treshold": 0,
          "algorithm": "t2auto",
          "byte_inserted": 1596605,
          "byte_miss": 1596605,
          "byte_read": 3469916,
          "byte_reinserted": 290485,
          "hit": 3469916,
          "inserted": 1596605,
          "layer": 0,
          "miss_ratio": 0.31512846783818715,
          "reinserted": 290485,
          "req": 5066521
        }
      ],
      "miss_ratio": 0.31512846783818715,
      "req": 5066521
    }
  ],
  "trace": "tencentBlock.ns20760.oracleGeneral.zst"
}