{
  "dram_cache_size": 39,
  "flash_cache_size": 3938,
  "results": [
    {
      "hit": 2389162,
      "iteration": 0,
      "metrics": [
        {
          "admission_treshold": 0,
          "algorithm": "t6auto",
          "byte_inserted": 1210773,
          "byte_miss": 1210773,
          "byte_read": 2389162,
          "byte_reinserted": 355325,
          "hit": 2389162,
          "inserted": 1210773,
          "layer": 0,
          "miss_ratio": 0.3363319059927471,
          "reinserted": 355325,
          "req": 3599935
        }
      ],
      "miss_ratio": 0.3363319059927471,
      "req": 3599935
    }
  ],
  "trace": "tencentBlock.ns6717.oracleGeneral.zst"
}