{
  "dram_cache_size": 23,
  "flash_cache_size": 2377,
  "results": [
    {
      "hit": 1023162,
      "iteration": 0,
      "metrics": [
        {
          "admission_treshold": 0,
          "algorithm": "q2auto",
          "byte_inserted": 848703,
          "byte_miss": 848703,
          "byte_read": 1023162,
          "byte_reinserted": 71864,
          "hit": 1023162,
          "inserted": 848703,
          "layer": 0,
          "miss_ratio": 0.453399684272103,
          "reinserted": 71864,
          "req": 1871865
        }
      ],
      "miss_ratio": 0.453399684272103,
      "req": 1871865
    }
  ],
  "trace": "tencentBlock.ns14337.oracleGeneral.zst"
}