{
  "dram_cache_size": 15,
  "flash_cache_size": 1505,
  "results": [
    {
      "hit": 927486,
      "iteration": 0,
      "metrics": [
        {
          "admission_treshold": 0,
          "algorithm": "time2-auto",
          "byte_inserted": 658672,
          "byte_miss": 658672,
          "byte_read": 927486,
          "byte_reinserted": 11094,
          "hit": 927486,
          "inserted": 658672,
          "layer": 0,
          "miss_ratio": 0.41526254004960417,
          "reinserted": 11094,
          "req": 1586158
        }
      ],
      "miss_ratio": 0.41526254004960417,
      "req": 1586158
    }
  ],
  "trace": "tencentBlock.ns21298.oracleGeneral.zst"
}