{
  "dram_cache_size": 9,
  "flash_cache_size": 952,
  "results": [
    {
      "hit": 2029063,
      "iteration": 0,
      "metrics": [
        {
          "admission_treshold": 0,
          "algorithm": "gclock",
          "byte_inserted": 462585,
          "byte_miss": 462585,
          "byte_read": 2029063,
          "byte_reinserted": 114843,
          "hit": 2029063,
          "inserted": 462585,
          "layer": 0,
          "miss_ratio": 0.18565423366382405,
          "reinserted": 114843,
          "req": 2491648
        }
      ],
      "miss_ratio": 0.18565423366382405,
      "req": 2491648
    }
  ],
  "trace": "tencentBlock.ns21047.oracleGeneral.zst"
}