{
  "dram_cache_size": 497,
  "flash_cache_size": 49779,
  "results": [
    {
      "hit": 149010131,
      "iteration": 0,
      "metrics": [
        {
          "admission_treshold": 0,
          "algorithm": "dclock",
          "byte_inserted": 116574476,
          "byte_miss": 116574476,
          "byte_read": 149010131,
          "byte_reinserted": 64503572,
          "hit": 149010131,
          "inserted": 116574476,
          "layer": 0,
          "miss_ratio": 0.43893536344898176,
          "reinserted": 64503572,
          "req": 265584607
        }
      ],
      "miss_ratio": 0.43893536344898176,
      "req": 265584607
    }
  ],
  "trace": "wiki_2019u.oracleGeneral.sample10.zst"
}