{
  "dram_cache_size": 60,
  "flash_cache_size": 6022,
  "results": [
    {
      "hit": 7076598,
      "iteration": 0,
      "metrics": [
        {
          "admission_treshold": 0,
          "algorithm": "dclock",
          "byte_inserted": 889734,
          "byte_miss": 889734,
          "byte_read": 7076598,
          "byte_reinserted": 135807,
          "hit": 7076598,
          "inserted": 889734,
          "layer": 0,
          "miss_ratio": 0.1116867838297475,
          "reinserted": 135807,
          "req": 7966332
        }
      ],
      "miss_ratio": 0.1116867838297475,
      "req": 7966332
    }
  ],
  "trace": "tencentBlock.ns12804.oracleGeneral.zst"
}