{
  "dram_cache_size": 14,
  "flash_cache_size": 1446,
  "results": [
    {
      "hit": 544829,
      "iteration": 0,
      "metrics": [
        {
          "admission_treshold": 0,
          "algorithm": "t3auto",
          "byte_inserted": 651228,
          "byte_miss": 651228,
          "byte_read": 544829,
          "byte_reinserted": 91077,
          "hit": 544829,
          "inserted": 651228,
          "layer": 0,
          "miss_ratio": 0.5444790674691925,
          "reinserted": 91077,
          "req": 1196057
        }
      ],
      "miss_ratio": 0.5444790674691925,
      "req": 1196057
    }
  ],
  "trace": "akamai_nyc.ns97.oracleGeneral.bin.zst"
}