{
  "dram_cache_size": 31,
  "flash_cache_size": 3127,
  "results": [
    {
      "hit": 1189729,
      "iteration": 0,
      "metrics": [
        {
          "admission_treshold": 0,
          "algorithm": "g2clock",
          "byte_inserted": 1209392,
          "byte_miss": 1209392,
          "byte_read": 1189729,
          "byte_reinserted": 265689,
          "hit": 1189729,
          "inserted": 1209392,
          "layer": 0,
          "miss_ratio": 0.5040979592108943,
          "reinserted": 265689,
          "req": 2399121
        }
      ],
      "miss_ratio": 0.5040979592108943,
      "req": 2399121
    }
  ],
  "trace": "tencentBlock.ns7207.oracleGeneral.zst"
}