{
  "dram_cache_size": 33,
  "flash_cache_size": 3364,
  "results": [
    {
      "hit": 16579782,
      "iteration": 0,
      "metrics": [
        {
          "admission_treshold": 0,
          "algorithm": "d3clock",
          "byte_inserted": 1706042,
          "byte_miss": 1706042,
          "byte_read": 16579782,
          "byte_reinserted": 1131041,
          "hit": 16579782,
          "inserted": 1706042,
          "layer": 0,
          "miss_ratio": 0.09329861208332746,
          "reinserted": 1131041,
          "req": 18285824
        }
      ],
      "miss_ratio": 0.09329861208332746,
      "req": 18285824
    }
  ],
  "trace": "tencentBlock.ns11314.oracleGeneral.zst"
}