{
  "dram_cache_size": 22,
  "flash_cache_size": 2235,
  "results": [
    {
      "hit": 1879333,
      "iteration": 0,
      "metrics": [
        {
          "admission_treshold": 0,
          "algorithm": "t3auto",
          "byte_inserted": 982800,
          "byte_miss": 982800,
          "byte_read": 1879333,
          "byte_reinserted": 145059,
          "hit": 1879333,
          "inserted": 982800,
          "layer": 0,
          "miss_ratio": 0.34338026919084474,
          "reinserted": 145059,
          "req": 2862133
        }
      ],
      "miss_ratio": 0.34338026919084474,
      "req": 2862133
    }
  ],
  "trace": "tencentBlock.ns18557.oracleGeneral.zst"
}