{
  "dram_cache_size": 7,
  "flash_cache_size": 798,
  "results": [
    {
      "hit": 2040007,
      "iteration": 0,
      "metrics": [
        {
          "admission_treshold": 0,
          "algorithm": "dclock",
          "byte_inserted": 489119,
          "byte_miss": 489119,
          "byte_read": 2040007,
          "byte_reinserted": 355443,
          "hit": 2040007,
          "inserted": 489119,
          "layer": 0,
          "miss_ratio": 0.19339447698533008,
          "reinserted": 355443,
          "req": 2529126
        }
      ],
      "miss_ratio": 0.19339447698533008,
      "req": 2529126
    }
  ],
  "trace": "tencentBlock.ns3662.oracleGeneral.zst"
}