{
  "dram_cache_size": 20,
  "flash_cache_size": 2092,
  "results": [
    {
      "hit": 2086562,
      "iteration": 0,
      "metrics": [
        {
          "admission_treshold": 0,
          "algorithm": "g2clock",
          "byte_inserted": 1368549,
          "byte_miss": 1368549,
          "byte_read": 2086562,
          "byte_reinserted": 232847,
          "hit": 2086562,
          "inserted": 1368549,
          "layer": 0,
          "miss_ratio": 0.3960940762829327,
          "reinserted": 232847,
          "req": 3455111
        }
      ],
      "miss_ratio": 0.3960940762829327,
      "req": 3455111
    }
  ],
  "trace": "tencentBlock.ns3284.oracleGeneral.zst"
}