{
  "dram_cache_size": 69,
  "flash_cache_size": 6979,
  "results": [
    {
      "hit": 7245445,
      "iteration": 0,
      "metrics": [
        {
          "admission_treshold": 0,
          "algorithm": "dclock",
          "byte_inserted": 2489227,
          "byte_miss": 2489227,
          "byte_read": 7245445,
          "byte_reinserted": 76539,
          "hit": 7245445,
          "inserted": 2489227,
          "layer": 0,
          "miss_ratio": 0.2557073314848205,
          "reinserted": 76539,
          "req": 9734672
        }
      ],
      "miss_ratio": 0.2557073314848205,
      "req": 9734672
    }
  ],
  "trace": "tencentBlock.ns2878.oracleGeneral.zst"
}