{
  "dram_cache_size": 9,
  "flash_cache_size": 945,
  "results": [
    {
      "hit": 884938,
      "iteration": 0,
      "metrics": [
        {
          "admission_treshold": 0,
          "algorithm": "q2auto",
          "byte_inserted": 648693,
          "byte_miss": 648693,
          "byte_read": 884938,
          "byte_reinserted": 69269,
          "hit": 884938,
          "inserted": 648693,
          "layer": 0,
          "miss_ratio": 0.422978539166201,
          "reinserted": 69269,
          "req": 1533631
        }
      ],
      "miss_ratio": 0.422978539166201,
      "req": 1533631
    }
  ],
  "trace": "tencentBlock.ns19050.oracleGeneral.zst"
}