{
  "dram_cache_size": 7,
  "flash_cache_size": 722,
  "results": [
    {
      "hit": 2209028,
      "iteration": 0,
      "metrics": [
        {
          "admission_treshold": 0,
          "algorithm": "gclock",
          "byte_inserted": 516026,
          "byte_miss": 516026,
          "byte_read": 2209028,
          "byte_reinserted": 401611,
          "hit": 2209028,
          "inserted": 516026,
          "layer": 0,
          "miss_ratio": 0.18936358692341515,
          "reinserted": 401611,
          "req": 2725054
        }
      ],
      "miss_ratio": 0.18936358692341515,
      "req": 2725054
    }
  ],
  "trace": "tencentBlock.ns1985.oracleGeneral.zst"
}