{
  "dram_cache_size": 19,
  "flash_cache_size": 1913,
  "results": [
    {
      "hit": 1599854,
      "iteration": 0,
      "metrics": [
        {
          "admission_treshold": 0,
          "algorithm": "tauto",
          "byte_inserted": 2650464,
          "byte_miss": 2650464,
          "byte_read": 1599854,
          "byte_reinserted": 292057,
          "hit": 1599854,
          "inserted": 2650464,
          "layer": 0,
          "miss_ratio": 0.6235919288862621,
          "reinserted": 292057,
          "req": 4250318
        }
      ],
      "miss_ratio": 0.6235919288862621,
      "req": 4250318
    }
  ],
  "trace": "cf_allcolo.ns361.oracleGeneral.zst"
}