{
  "dram_cache_size": 40582,
  "flash_cache_size": 4058247,
  "results": [
    {
      "hit": 99483101,
      "iteration": 0,
      "metrics": [
        {
          "admission_treshold": 0,
          "algorithm": "tauto",
          "byte_inserted": 86846014331,
          "byte_miss": 86846014331,
          "byte_read": 1292271871512,
          "byte_reinserted": 85788266315,
          "hit": 99483101,
          "inserted": 2710203,
          "layer": 0,
          "miss_ratio": 0.02652035792873475,
          "reinserted": 2905159,
          "req": 102193304
        }
      ],
      "miss_ratio": 0.02652035792873475,
      "req": 102193304
    }
  ],
  "trace": "cf_allcolo.ns43.oracleGeneral.zst"
}