{
  "dram_cache_size": 160,
  "flash_cache_size": 16011,
  "results": [
    {
      "hit": 576720939,
      "iteration": 0,
      "metrics": [
        {
          "admission_treshold": 0,
          "algorithm": "qand-clock-v2",
          "byte_inserted": 222574328,
          "byte_miss": 222574328,
          "byte_read": 576720939,
          "byte_reinserted": 208809609,
          "hit": 576720939,
          "inserted": 222574328,
          "layer": 0,
          "miss_ratio": 0.27846321276915553,
          "reinserted": 208809609,
          "req": 799295267
        }
      ],
      "miss_ratio": 0.27846321276915553,
      "req": 799295267
    }
  ],
  "trace": "cluster49.oracleGeneral.zst"
}