{
  "dram_cache_size": 15,
  "flash_cache_size": 1551,
  "results": [
    {
      "hit": 3450811,
      "iteration": 0,
      "metrics": [
        {
          "admission_treshold": 0,
          "algorithm": "s3fclock-sequential",
          "byte_inserted": 652818,
          "byte_miss": 652818,
          "byte_read": 3450811,
          "byte_reinserted": 122956,
          "hit": 3450811,
          "inserted": 652818,
          "layer": 0,
          "miss_ratio": 0.15908309450001445,
          "reinserted": 122956,
          "req": 4103629
        }
      ],
      "miss_ratio": 0.15908309450001445,
      "req": 4103629
    }
  ],
  "trace": "tencentBlock.ns9519.oracleGeneral.zst"
}