{
  "dram_cache_size": 66,
  "flash_cache_size": 6687,
  "results": [
    {
      "hit": 2962613,
      "iteration": 0,
      "metrics": [
        {
          "admission_treshold": 0,
          "algorithm": "time2-auto",
          "byte_inserted": 672524,
          "byte_miss": 672524,
          "byte_read": 2962613,
          "byte_reinserted": 598,
          "hit": 2962613,
          "inserted": 672524,
          "layer": 0,
          "miss_ratio": 0.18500650732008173,
          "reinserted": 598,
          "req": 3635137
        }
      ],
      "miss_ratio": 0.18500650732008173,
      "req": 3635137
    }
  ],
  "trace": "akamai_sjc.ns128.oracleGeneral.bin.zst"
}