{
  "dram_cache_size": 343,
  "flash_cache_size": 34326,
  "results": [
    {
      "hit": 105754,
      "iteration": 0,
      "metrics": [
        {
          "admission_treshold": 0,
          "algorithm": "cm-clock",
          "byte_inserted": 6694246,
          "byte_miss": 6694246,
          "byte_read": 105754,
          "byte_reinserted": 11761,
          "hit": 105754,
          "inserted": 6694246,
          "layer": 0,
          "miss_ratio": 0.9844479411764706,
          "reinserted": 11761,
          "req": 6800000
        }
      ],
      "miss_ratio": 0.9844479411764706,
      "req": 6800000
    }
  ],
  "trace": "io_traces.ns792.oracleGeneral.zst"
}