{
  "dram_cache_size": 2,
  "flash_cache_size": 274,
  "results": [
    {
      "hit": 1475357,
      "iteration": 0,
      "metrics": [
        {
          "admission_treshold": 0,
          "algorithm": "gclock",
          "byte_inserted": 135034,
          "byte_miss": 135034,
          "byte_read": 1475357,
          "byte_reinserted": 306769,
          "hit": 1475357,
          "inserted": 135034,
          "layer": 0,
          "miss_ratio": 0.083851685708626,
          "reinserted": 306769,
          "req": 1610391
        }
      ],
      "miss_ratio": 0.083851685708626,
      "req": 1610391
    }
  ],
  "trace": "cf_allcolo.ns2332.oracleGeneral.zst"
}