{
  "dram_cache_size": 43,
  "flash_cache_size": 4394,
  "results": [
    {
      "hit": 1948966,
      "iteration": 0,
      "metrics": [
        {
          "admission_treshold": 0,
          "algorithm": "time2-auto",
          "byte_inserted": 1054789,
          "byte_miss": 1054789,
          "byte_read": 1948966,
          "byte_reinserted": 115828,
          "hit": 1948966,
          "inserted": 1054789,
          "layer": 0,
          "miss_ratio": 0.3511568020694098,
          "reinserted": 115828,
          "req": 3003755
        }
      ],
      "miss_ratio": 0.3511568020694098,
      "req": 3003755
    }
  ],
  "trace": "cf_allcolo.ns2501.oracleGeneral.zst"
}