{
  "dram_cache_size": 5,
  "flash_cache_size": 551,
  "results": [
    {
      "hit": 26346616,
      "iteration": 0,
      "metrics": [
        {
          "admission_treshold": 0,
          "algorithm": "g2clock",
          "byte_inserted": 534572,
          "byte_miss": 534572,
          "byte_read": 26346616,
          "byte_reinserted": 1525898,
          "hit": 26346616,
          "inserted": 534572,
          "layer": 0,
          "miss_ratio": 0.019886472279424527,
          "reinserted": 1525898,
          "req": 26881188
        }
      ],
      "miss_ratio": 0.019886472279424527,
      "req": 26881188
    }
  ],
  "trace": "url_info_cache.0.oracleGeneral.sample10.zst"
}