{
  "dram_cache_size": 341,
  "flash_cache_size": 34189,
  "results": [
    {
      "hit": 16891997,
      "iteration": 0,
      "metrics": [
        {
          "admission_treshold": 0,
          "algorithm": "t5auto",
          "byte_inserted": 9182683,
          "byte_miss": 9182683,
          "byte_read": 16891997,
          "byte_reinserted": 2077567,
          "hit": 16891997,
          "inserted": 9182683,
          "layer": 0,
          "miss_ratio": 0.35216857886654795,
          "reinserted": 2077567,
          "req": 26074680
        }
      ],
      "miss_ratio": 0.35216857886654795,
      "req": 26074680
    }
  ],
  "trace": "tencentBlock.ns20699.oracleGeneral.zst"
}