{
  "dram_cache_size": 99,
  "flash_cache_size": 9950,
  "results": [
    {
      "hit": 24463533,
      "iteration": 0,
      "metrics": [
        {
          "admission_treshold": 0,
          "algorithm": "gclock",
          "byte_inserted": 1832375,
          "byte_miss": 1832375,
          "byte_read": 24463533,
          "byte_reinserted": 1027153,
          "hit": 24463533,
          "inserted": 1832375,
          "layer": 0,
          "miss_ratio": 0.06968289514855319,
          "reinserted": 1027153,
          "req": 26295908
        }
      ],
      "miss_ratio": 0.06968289514855319,
      "req": 26295908
    }
  ],
  "trace": "tencentBlock.ns8927.oracleGeneral.zst"
}