{
  "dram_cache_size": 2,
  "flash_cache_size": 294,
  "results": [
    {
      "hit": 16951924,
      "iteration": 0,
      "metrics": [
        {
          "admission_treshold": 0,
          "algorithm": "dclock",
          "byte_inserted": 2815584,
          "byte_miss": 2815584,
          "byte_read": 16951924,
          "byte_reinserted": 3307126,
          "hit": 16951924,
          "inserted": 2815584,
          "layer": 0,
          "miss_ratio": 0.1424349493117696,
          "reinserted": 3307126,
          "req": 19767508
        }
      ],
      "miss_ratio": 0.1424349493117696,
      "req": 19767508
    }
  ],
  "trace": "cf_allcolo.ns72.oracleGeneral.zst"
}