{
  "dram_cache_size": 16,
  "flash_cache_size": 1682,
  "results": [
    {
      "hit": 667024,
      "iteration": 0,
      "metrics": [
        {
          "admission_treshold": 0,
          "algorithm": "t5auto",
          "byte_inserted": 494022,
          "byte_miss": 494022,
          "byte_read": 667024,
          "byte_reinserted": 26157,
          "hit": 667024,
          "inserted": 494022,
          "layer": 0,
          "miss_ratio": 0.4254973532487085,
          "reinserted": 26157,
          "req": 1161046
        }
      ],
      "miss_ratio": 0.4254973532487085,
      "req": 1161046
    }
  ],
  "trace": "tencentBlock.ns18369.oracleGeneral.zst"
}