{
  "dram_cache_size": 0,
  "flash_cache_size": 15,
  "results": [
    {
      "hit": 1783186,
      "iteration": 0,
      "metrics": [
        {
          "admission_treshold": 0,
          "algorithm": "qand-clock",
          "byte_inserted": 23687,
          "byte_miss": 23687,
          "byte_read": 1783186,
          "byte_reinserted": 27435,
          "hit": 1783186,
          "inserted": 23687,
          "layer": 0,
          "miss_ratio": 0.013109388429623947,
          "reinserted": 27435,
          "req": 1806873
        }
      ],
      "miss_ratio": 0.013109388429623947,
      "req": 1806873
    }
  ],
  "trace": "cf_allcolo.ns176.oracleGeneral.zst"
}