{
  "dram_cache_size": 709,
  "flash_cache_size": 70971,
  "results": [
    {
      "hit": 5756587,
      "iteration": 0,
      "metrics": [
        {
          "admission_treshold": 0,
          "algorithm": "fifo",
          "byte_inserted": 714885,
          "byte_miss": 714885,
          "byte_read": 5756587,
          "byte_reinserted": 0,
          "hit": 5756587,
          "inserted": 714885,
          "layer": 0,
          "miss_ratio": 0.11046713946996911,
          "reinserted": 0,
          "req": 6471472
        }
      ],
      "miss_ratio": 0.11046713946996911,
      "req": 6471472
    }
  ],
  "trace": "cf_allcolo.ns612.oracleGeneral.zst"
}