{
  "dram_cache_size": 0,
  "flash_cache_size": 16,
  "results": [
    {
      "hit": 3184867,
      "iteration": 0,
      "metrics": [
        {
          "admission_treshold": 0,
          "algorithm": "fifo",
          "byte_inserted": 461,
          "byte_miss": 461,
          "byte_read": 3184867,
          "byte_reinserted": 0,
          "hit": 3184867,
          "inserted": 461,
          "layer": 0,
          "miss_ratio": 0.00014472606902649066,
          "reinserted": 0,
          "req": 3185328
        }
      ],
      "miss_ratio": 0.00014472606902649066,
      "req": 3185328
    }
  ],
  "trace": "cf_allcolo.ns968.oracleGeneral.zst"
}