{
  "dram_cache_size": 271,
  "flash_cache_size": 27169,
  "results": [
    {
      "hit": 641762,
      "iteration": 0,
      "metrics": [
        {
          "admission_treshold": 0,
          "algorithm": "qtime-clock",
          "byte_inserted": 418406,
          "byte_miss": 418406,
          "byte_read": 641762,
          "byte_reinserted": 51435,
          "hit": 641762,
          "inserted": 418406,
          "layer": 0,
          "miss_ratio": 0.39466009160812243,
          "reinserted": 51435,
          "req": 1060168
        }
      ],
      "miss_ratio": 0.39466009160812243,
      "req": 1060168
    }
  ],
  "trace": "cf_colo28.ns1540.oracleGeneral.zst"
}