{
  "dram_cache_size": 480,
  "flash_cache_size": 48075,
  "results": [
    {
      "hit": 187018924,
      "iteration": 0,
      "metrics": [
        {
          "admission_treshold": 0,
          "algorithm": "qand-clock",
          "byte_inserted": 78581076,
          "byte_miss": 78581076,
          "byte_read": 187018924,
          "byte_reinserted": 15474097,
          "hit": 187018924,
          "inserted": 78581076,
          "layer": 0,
          "miss_ratio": 0.2958624849397591,
          "reinserted": 15474097,
          "req": 265600000
        }
      ],
      "miss_ratio": 0.2958624849397591,
      "req": 265600000
    }
  ],
  "trace": "io_traces.ns7.oracleGeneral.zst"
}