{
  "dram_cache_size": 35,
  "flash_cache_size": 3554,
  "results": [
    {
      "hit": 66297613,
      "iteration": 0,
      "metrics": [
        {
          "admission_treshold": 0,
          "algorithm": "qor-clock",
          "byte_inserted": 58791923,
          "byte_miss": 58791923,
          "byte_read": 66297613,
          "byte_reinserted": 157281,
          "hit": 66297613,
          "inserted": 58791923,
          "layer": 0,
          "miss_ratio": 0.4699987295500081,
          "reinserted": 157281,
          "req": 125089536
        }
      ],
      "miss_ratio": 0.4699987295500081,
      "req": 125089536
    }
  ],
  "trace": "mechanic_failure_staging_cache.1.oracleGeneral.sample10.zst"
}