{
  "dram_cache_size": 20,
  "flash_cache_size": 2073,
  "results": [
    {
      "hit": 1017543,
      "iteration": 0,
      "metrics": [
        {
          "admission_treshold": 0,
          "algorithm": "qand-clock",
          "byte_inserted": 662777,
          "byte_miss": 662777,
          "byte_read": 1017543,
          "byte_reinserted": 111894,
          "hit": 1017543,
          "inserted": 662777,
          "layer": 0,
          "miss_ratio": 0.39443498857360504,
          "reinserted": 111894,
          "req": 1680320
        }
      ],
      "miss_ratio": 0.39443498857360504,
      "req": 1680320
    }
  ],
  "trace": "tencentBlock.ns3247.oracleGeneral.zst"
}