{
  "dram_cache_size": 19,
  "flash_cache_size": 1994,
  "results": [
    {
      "hit": 619500,
      "iteration": 0,
      "metrics": [
        {
          "admission_treshold": 0,
          "algorithm": "qand-clock",
          "byte_inserted": 587049,
          "byte_miss": 587049,
          "byte_read": 619500,
          "byte_reinserted": 24303,
          "hit": 619500,
          "inserted": 587049,
          "layer": 0,
          "miss_ratio": 0.48655214168674454,
          "reinserted": 24303,
          "req": 1206549
        }
      ],
      "miss_ratio": 0.48655214168674454,
      "req": 1206549
    }
  ],
  "trace": "tencentBlock.ns14644.oracleGeneral.zst"
}