{
  "dram_cache_size": 30,
  "flash_cache_size": 3041,
  "results": [
    {
      "hit": 4760759,
      "iteration": 0,
      "metrics": [
        {
          "admission_treshold": 0,
          "algorithm": "qtime-clock",
          "byte_inserted": 1648051,
          "byte_miss": 1648051,
          "byte_read": 4760759,
          "byte_reinserted": 426287,
          "hit": 4760759,
          "inserted": 1648051,
          "layer": 0,
          "miss_ratio": 0.25715398022409774,
          "reinserted": 426287,
          "req": 6408810
        }
      ],
      "miss_ratio": 0.25715398022409774,
      "req": 6408810
    }
  ],
  "trace": "tencentBlock.ns6237.oracleGeneral.zst"
}