{
  "dram_cache_size": 17,
  "flash_cache_size": 1758,
  "results": [
    {
      "hit": 482305,
      "iteration": 0,
      "metrics": [
        {
          "admission_treshold": 0,
          "algorithm": "qor-clock",
          "byte_inserted": 524375,
          "byte_miss": 524375,
          "byte_read": 482305,
          "byte_reinserted": 7326,
          "hit": 482305,
          "inserted": 524375,
          "layer": 0,
          "miss_ratio": 0.5208954186037271,
          "reinserted": 7326,
          "req": 1006680
        }
      ],
      "miss_ratio": 0.5208954186037271,
      "req": 1006680
    }
  ],
  "trace": "tencentBlock.ns10560.oracleGeneral.zst"
}