{
  "dram_cache_size": 14,
  "flash_cache_size": 1474,
  "results": [
    {
      "hit": 1953342,
      "iteration": 0,
      "metrics": [
        {
          "admission_treshold": 0,
          "algorithm": "q-clock",
          "byte_inserted": 820690,
          "byte_miss": 820690,
          "byte_read": 1953342,
          "byte_reinserted": 194479,
          "hit": 1953342,
          "inserted": 820690,
          "layer": 0,
          "miss_ratio": 0.29584734422674286,
          "reinserted": 194479,
          "req": 2774032
        }
      ],
      "miss_ratio": 0.29584734422674286,
      "req": 2774032
    }
  ],
  "trace": "tencentBlock.ns12006.oracleGeneral.zst"
}