{
  "dram_cache_size": 33,
  "flash_cache_size": 3354,
  "results": [
    {
      "hit": 1405354,
      "iteration": 0,
      "metrics": [
        {
          "admission_treshold": 0,
          "algorithm": "qauto",
          "byte_inserted": 2219997,
          "byte_miss": 2219997,
          "byte_read": 1405354,
          "byte_reinserted": 129427,
          "hit": 1405354,
          "inserted": 2219997,
          "layer": 0,
          "miss_ratio": 0.6123536727892003,
          "reinserted": 129427,
          "req": 3625351
        }
      ],
      "miss_ratio": 0.6123536727892003,
      "req": 3625351
    }
  ],
  "trace": "tencentBlock.ns14871.oracleGeneral.zst"
}