{
  "dram_cache_size": 57,
  "flash_cache_size": 5787,
  "results": [
    {
      "hit": 3088188,
      "iteration": 0,
      "metrics": [
        {
          "admission_treshold": 0,
          "algorithm": "qtime-clock",
          "byte_inserted": 2562732,
          "byte_miss": 2562732,
          "byte_read": 3088188,
          "byte_reinserted": 334007,
          "hit": 3088188,
          "inserted": 2562732,
          "layer": 0,
          "miss_ratio": 0.4535070395616997,
          "reinserted": 334007,
          "req": 5650920
        }
      ],
      "miss_ratio": 0.4535070395616997,
      "req": 5650920
    }
  ],
  "trace": "tencentBlock.ns18849.oracleGeneral.zst"
}