{
  "dram_cache_size": 296,
  "flash_cache_size": 29654,
  "results": [
    {
      "hit": 2602555,
      "iteration": 0,
      "metrics": [
        {
          "admission_treshold": 0,
          "algorithm": "fifo",
          "byte_inserted": 771495,
          "byte_miss": 771495,
          "byte_read": 2602555,
          "byte_reinserted": 0,
          "hit": 2602555,
          "inserted": 771495,
          "layer": 0,
          "miss_ratio": 0.22865547339251047,
          "reinserted": 0,
          "req": 3374050
        }
      ],
      "miss_ratio": 0.22865547339251047,
      "req": 3374050
    }
  ],
  "trace": "tencentBlock.ns20969.oracleGeneral.zst"
}