{
  "dram_cache_size": 28,
  "flash_cache_size": 2830,
  "results": [
    {
      "hit": 2142763,
      "iteration": 0,
      "metrics": [
        {
          "admission_treshold": 0,
          "algorithm": "qand-clock",
          "byte_inserted": 859245,
          "byte_miss": 859245,
          "byte_read": 2142763,
          "byte_reinserted": 410513,
          "hit": 2142763,
          "inserted": 859245,
          "layer": 0,
          "miss_ratio": 0.28622342112346133,
          "reinserted": 410513,
          "req": 3002008
        }
      ],
      "miss_ratio": 0.28622342112346133,
      "req": 3002008
    }
  ],
  "trace": "tencentBlock.ns2767.oracleGeneral.zst"
}