{
  "dram_cache_size": 340,
  "flash_cache_size": 34046,
  "results": [
    {
      "hit": 2699497,
      "iteration": 0,
      "metrics": [
        {
          "admission_treshold": 0,
          "algorithm": "q-clock",
          "byte_inserted": 582607,
          "byte_miss": 582607,
          "byte_read": 2699497,
          "byte_reinserted": 215219,
          "hit": 2699497,
          "inserted": 582607,
          "layer": 0,
          "miss_ratio": 0.1775102190546064,
          "reinserted": 215219,
          "req": 3282104
        }
      ],
      "miss_ratio": 0.1775102190546064,
      "req": 3282104
    }
  ],
  "trace": "tencentBlock.ns14542.oracleGeneral.zst"
}