{
  "dram_cache_size": 5,
  "flash_cache_size": 578,
  "results": [
    {
      "hit": 142809686,
      "iteration": 0,
      "metrics": [
        {
          "admission_treshold": 0,
          "algorithm": "qand-clock",
          "byte_inserted": 4395703,
          "byte_miss": 4395703,
          "byte_read": 142809686,
          "byte_reinserted": 10069251,
          "hit": 142809686,
          "inserted": 4395703,
          "layer": 0,
          "miss_ratio": 0.029861019558190205,
          "reinserted": 10069251,
          "req": 147205389
        }
      ],
      "miss_ratio": 0.029861019558190205,
      "req": 147205389
    }
  ],
  "trace": "tencentBlock.ns5512.oracleGeneral.zst"
}