{
  "dram_cache_size": 25,
  "flash_cache_size": 2530,
  "results": [
    {
      "hit": 2077678,
      "iteration": 0,
      "metrics": [
        {
          "admission_treshold": 0,
          "algorithm": "qtime-clock",
          "byte_inserted": 809460,
          "byte_miss": 809460,
          "byte_read": 2077678,
          "byte_reinserted": 309218,
          "hit": 2077678,
          "inserted": 809460,
          "layer": 0,
          "miss_ratio": 0.280367616650122,
          "reinserted": 309218,
          "req": 2887138
        }
      ],
      "miss_ratio": 0.280367616650122,
      "req": 2887138
    }
  ],
  "trace": "tencentBlock.ns11968.oracleGeneral.zst"
}