{
  "dram_cache_size": 8,
  "flash_cache_size": 887,
  "results": [
    {
      "hit": 2187141,
      "iteration": 0,
      "metrics": [
        {
          "admission_treshold": 0,
          "algorithm": "qtime-clock",
          "byte_inserted": 284485,
          "byte_miss": 284485,
          "byte_read": 2187141,
          "byte_reinserted": 168910,
          "hit": 2187141,
          "inserted": 284485,
          "layer": 0,
          "miss_ratio": 0.11510034285122428,
          "reinserted": 168910,
          "req": 2471626
        }
      ],
      "miss_ratio": 0.11510034285122428,
      "req": 2471626
    }
  ],
  "trace": "tencentBlock.ns4170.oracleGeneral.zst"
}