{
  "dram_cache_size": 32,
  "flash_cache_size": 3205,
  "results": [
    {
      "hit": 4675768,
      "iteration": 0,
      "metrics": [
        {
          "admission_treshold": 0,
          "algorithm": "qand-clock",
          "byte_inserted": 1096291,
          "byte_miss": 1096291,
          "byte_read": 4675768,
          "byte_reinserted": 418450,
          "hit": 4675768,
          "inserted": 1096291,
          "layer": 0,
          "miss_ratio": 0.18993066425689686,
          "reinserted": 418450,
          "req": 5772059
        }
      ],
      "miss_ratio": 0.18993066425689686,
      "req": 5772059
    }
  ],
  "trace": "tencentBlock.ns4276.oracleGeneral.zst"
}