{
  "dram_cache_size": 12,
  "flash_cache_size": 1289,
  "results": [
    {
      "hit": 432568,
      "iteration": 0,
      "metrics": [
        {
          "admission_treshold": 0,
          "algorithm": "g2clock",
          "byte_inserted": 1167432,
          "byte_miss": 1167432,
          "byte_read": 432568,
          "byte_reinserted": 106680,
          "hit": 432568,
          "inserted": 1167432,
          "layer": 0,
          "miss_ratio": 0.729645,
          "reinserted": 106680,
          "req": 1600000
        }
      ],
      "miss_ratio": 0.729645,
      "req": 1600000
    }
  ],
  "trace": "io_traces.ns550.oracleGeneral.zst"
}