{
  "dram_cache_size": 31,
  "flash_cache_size": 3125,
  "results": [
    {
      "hit": 1138534,
      "iteration": 0,
      "metrics": [
        {
          "admission_treshold": 0,
          "algorithm": "qtime-clock",
          "byte_inserted": 414559,
          "byte_miss": 414559,
          "byte_read": 1138534,
          "byte_reinserted": 49653,
          "hit": 1138534,
          "inserted": 414559,
          "layer": 0,
          "miss_ratio": 0.26692477527102365,
          "reinserted": 49653,
          "req": 1553093
        }
      ],
      "miss_ratio": 0.26692477527102365,
      "req": 1553093
    }
  ],
  "trace": "cf_colo28.ns869.oracleGeneral.zst"
}