{
  "dram_cache_size": 26,
  "flash_cache_size": 2692,
  "results": [
    {
      "hit": 15790015,
      "iteration": 0,
      "metrics": [
        {
          "admission_treshold": 0,
          "algorithm": "d3clock",
          "byte_inserted": 1297447,
          "byte_miss": 1297447,
          "byte_read": 15790015,
          "byte_reinserted": 1423368,
          "hit": 15790015,
          "inserted": 1297447,
          "layer": 0,
          "miss_ratio": 0.07592976651535499,
          "reinserted": 1423368,
          "req": 17087462
        }
      ],
      "miss_ratio": 0.07592976651535499,
      "req": 17087462
    }
  ],
  "trace": "cf_allcolo.ns241.oracleGeneral.zst"
}