{
  "dram_cache_size": 431,
  "flash_cache_size": 43162,
  "results": [
    {
      "hit": 446409919,
      "iteration": 0,
      "metrics": [
        {
          "admission_treshold": 0,
          "algorithm": "dclock",
          "byte_inserted": 18990081,
          "byte_miss": 18990081,
          "byte_read": 446409919,
          "byte_reinserted": 32797138,
          "hit": 446409919,
          "inserted": 18990081,
          "layer": 0,
          "miss_ratio": 0.040803783841856456,
          "reinserted": 32797138,
          "req": 465400000
        }
      ],
      "miss_ratio": 0.040803783841856456,
      "req": 465400000
    }
  ],
  "trace": "io_traces.ns206.oracleGeneral.zst"
}