{
  "dram_cache_size": 50,
  "flash_cache_size": 5071,
  "results": [
    {
      "hit": 3128053,
      "iteration": 0,
      "metrics": [
        {
          "admission_treshold": 0,
          "algorithm": "dclock",
          "byte_inserted": 1786843,
          "byte_miss": 1786843,
          "byte_read": 3128053,
          "byte_reinserted": 1132518,
          "hit": 3128053,
          "inserted": 1786843,
          "layer": 0,
          "miss_ratio": 0.3635566245959223,
          "reinserted": 1132518,
          "req": 4914896
        }
      ],
      "miss_ratio": 0.3635566245959223,
      "req": 4914896
    }
  ],
  "trace": "tencentBlock.ns16105.oracleGeneral.zst"
}