{
  "dram_cache_size": 149,
  "flash_cache_size": 14996,
  "results": [
    {
      "hit": 43881499,
      "iteration": 0,
      "metrics": [
        {
          "admission_treshold": 0,
          "algorithm": "gclock",
          "byte_inserted": 151942803,
          "byte_miss": 151942803,
          "byte_read": 43881499,
          "byte_reinserted": 16033711,
          "hit": 43881499,
          "inserted": 151942803,
          "layer": 0,
          "miss_ratio": 0.7759139261479405,
          "reinserted": 16033711,
          "req": 195824302
        }
      ],
      "miss_ratio": 0.7759139261479405,
      "req": 195824302
    }
  ],
  "trace": "tencentBlock.ns1351.oracleGeneral.zst"
}