{
  "dram_cache_size": 834,
  "flash_cache_size": 83455,
  "results": [
    {
      "hit": 287581611,
      "iteration": 0,
      "metrics": [
        {
          "admission_treshold": 0,
          "algorithm": "sxfifo",
          "byte_inserted": 25978687,
          "byte_miss": 25978687,
          "byte_read": 287581611,
          "byte_reinserted": 12823543,
          "hit": 287581611,
          "inserted": 25978687,
          "layer": 0,
          "miss_ratio": 0.08285068985359878,
          "reinserted": 12823543,
          "req": 313560298
        }
      ],
      "miss_ratio": 0.08285068985359878,
      "req": 313560298
    }
  ],
  "trace": "ibis_api_cache.1.oracleGeneral.sample10.zst"
}