{
  "dram_cache_size": 14,
  "flash_cache_size": 1406,
  "results": [
    {
      "hit": 837676,
      "iteration": 0,
      "metrics": [
        {
          "admission_treshold": 0,
          "algorithm": "d3clock",
          "byte_inserted": 520166,
          "byte_miss": 520166,
          "byte_read": 837676,
          "byte_reinserted": 28294,
          "hit": 837676,
          "inserted": 520166,
          "layer": 0,
          "miss_ratio": 0.3830828623654299,
          "reinserted": 28294,
          "req": 1357842
        }
      ],
      "miss_ratio": 0.3830828623654299,
      "req": 1357842
    }
  ],
  "trace": "tencentBlock.ns8287.oracleGeneral.zst"
}