{
  "dram_cache_size": 33,
  "flash_cache_size": 3354,
  "results": [
    {
      "hit": 1494996,
      "iteration": 0,
      "metrics": [
        {
          "admission_treshold": 0,
          "algorithm": "d3clock",
          "byte_inserted": 2130355,
          "byte_miss": 2130355,
          "byte_read": 1494996,
          "byte_reinserted": 387803,
          "hit": 1494996,
          "inserted": 2130355,
          "layer": 0,
          "miss_ratio": 0.5876272394038535,
          "reinserted": 387803,
          "req": 3625351
        }
      ],
      "miss_ratio": 0.5876272394038535,
      "req": 3625351
    }
  ],
  "trace": "tencentBlock.ns14871.oracleGeneral.zst"
}